{
  "info": {
    "name": "WND Dialer API v1-v2",
    "_postman_id": "e66b4d26-b20c-45c3-9923-2dd7af309a4a",
    "description": "Collection for backward-compatible v1/v2 API validation via Accept header.",
    "schema": "https://schema.getpostman.com/json/collection/v2.1.0/collection.json"
  },
  "item": [
    {
      "name": "Plans (v1 default)",
      "request": {
        "method": "GET",
        "header": [
          {
            "key": "Accept",
            "value": "application/json"
          }
        ],
        "url": {
          "raw": "{{baseUrl}}/api/v1/plans",
          "host": ["{{baseUrl}}"],
          "path": ["api", "v1", "plans"]
        }
      }
    },
    {
      "name": "Plans (v2)",
      "request": {
        "method": "GET",
        "header": [
          {
            "key": "Accept",
            "value": "application/vnd.wnddialer.v2+json"
          }
        ],
        "url": {
          "raw": "{{baseUrl}}/api/v1/plans",
          "host": ["{{baseUrl}}"],
          "path": ["api", "v1", "plans"]
        }
      }
    },
    {
      "name": "Register",
      "request": {
        "method": "POST",
        "header": [
          {
            "key": "Content-Type",
            "value": "application/json"
          },
          {
            "key": "Accept",
            "value": "application/vnd.wnddialer.v2+json"
          }
        ],
        "body": {
          "mode": "raw",
          "raw": "{\n  \"company_name\": \"WND Labs\",\n  \"first_name\": \"Owner\",\n  \"last_name\": \"User\",\n  \"email\": \"owner@example.com\",\n  \"password\": \"password123\",\n  \"password_confirmation\": \"password123\",\n  \"timezone\": \"UTC\"\n}"
        },
        "url": {
          "raw": "{{baseUrl}}/api/v1/auth/register",
          "host": ["{{baseUrl}}"],
          "path": ["api", "v1", "auth", "register"]
        }
      }
    },
    {
      "name": "Login",
      "request": {
        "method": "POST",
        "header": [
          {
            "key": "Content-Type",
            "value": "application/json"
          },
          {
            "key": "Accept",
            "value": "application/vnd.wnddialer.v2+json"
          }
        ],
        "body": {
          "mode": "raw",
          "raw": "{\n  \"email\": \"owner@example.com\",\n  \"password\": \"password123\"\n}"
        },
        "url": {
          "raw": "{{baseUrl}}/api/v1/auth/login",
          "host": ["{{baseUrl}}"],
          "path": ["api", "v1", "auth", "login"]
        }
      }
    },
    {
      "name": "Me",
      "request": {
        "method": "GET",
        "header": [
          {
            "key": "Authorization",
            "value": "Bearer {{token}}"
          },
          {
            "key": "X-Tenant-Id",
            "value": "{{tenantId}}"
          },
          {
            "key": "Accept",
            "value": "application/vnd.wnddialer.v2+json"
          }
        ],
        "url": {
          "raw": "{{baseUrl}}/api/v1/auth/me",
          "host": ["{{baseUrl}}"],
          "path": ["api", "v1", "auth", "me"]
        }
      }
    },
    {
      "name": "Create Call",
      "request": {
        "method": "POST",
        "header": [
          {
            "key": "Authorization",
            "value": "Bearer {{token}}"
          },
          {
            "key": "X-Tenant-Id",
            "value": "{{tenantId}}"
          },
          {
            "key": "Content-Type",
            "value": "application/json"
          },
          {
            "key": "Accept",
            "value": "application/vnd.wnddialer.v2+json"
          }
        ],
        "body": {
          "mode": "raw",
          "raw": "{\n  \"to_number\": \"+15550000002\",\n  \"from_number\": \"+15550000001\"\n}"
        },
        "url": {
          "raw": "{{baseUrl}}/api/v1/calls",
          "host": ["{{baseUrl}}"],
          "path": ["api", "v1", "calls"]
        }
      }
    },
    {
      "name": "Start Campaign",
      "request": {
        "method": "POST",
        "header": [
          {
            "key": "Authorization",
            "value": "Bearer {{token}}"
          },
          {
            "key": "X-Tenant-Id",
            "value": "{{tenantId}}"
          },
          {
            "key": "Accept",
            "value": "application/vnd.wnddialer.v2+json"
          }
        ],
        "url": {
          "raw": "{{baseUrl}}/api/v1/campaigns/{{campaignId}}/start",
          "host": ["{{baseUrl}}"],
          "path": ["api", "v1", "campaigns", "{{campaignId}}", "start"]
        }
      }
    }
  ],
  "variable": [
    {
      "key": "baseUrl",
      "value": "http://localhost:8000"
    },
    {
      "key": "token",
      "value": ""
    },
    {
      "key": "tenantId",
      "value": ""
    },
    {
      "key": "campaignId",
      "value": ""
    }
  ]
}
